data/mlb_draft_cache/1965.json
data/mlb_draft_cache/1966.json
data/mlb_draft_cache/1967.json
data/mlb_draft_cache/1968.json
data/mlb_draft_cache/1969.json
data/mlb_draft_cache/1970.json
data/mlb_draft_cache/1971.json
data/mlb_draft_cache/1972.json
data/mlb_draft_cache/1973.json
data/mlb_draft_cache/1974.json
data/mlb_draft_cache/1975.json
data/mlb_draft_cache/1976.json
data/mlb_draft_cache/1977.json
data/mlb_draft_cache/1978.json
data/mlb_draft_cache/1979.json
data/mlb_draft_cache/1980.json
data/mlb_draft_cache/1981.json
data/mlb_draft_cache/1982.json
data/mlb_draft_cache/1983.json
data/mlb_draft_cache/1984.json
data/mlb_draft_cache/1985.json
data/mlb_draft_cache/1986.json
data/mlb_draft_cache/1987.json
data/mlb_draft_cache/1988.json
data/mlb_draft_cache/1989.json
data/mlb_draft_cache/1990.json
data/mlb_draft_cache/1991.json
data/mlb_draft_cache/1992.json
data/mlb_draft_cache/1993.json
data/mlb_draft_cache/1994.json
data/mlb_draft_cache/1995.json
data/mlb_draft_cache/1996.json
data/mlb_draft_cache/1997.json
data/mlb_draft_cache/1998.json
data/mlb_draft_cache/1999.json
data/mlb_draft_cache/2000.json
data/mlb_draft_cache/2001.json
data/mlb_draft_cache/2002.json
data/mlb_draft_cache/2003.json
data/mlb_draft_cache/2004.json
data/mlb_draft_cache/2005.json
data/mlb_draft_cache/2006.json
data/mlb_draft_cache/2007.json
data/mlb_draft_cache/2008.json
data/mlb_draft_cache/2009.json
data/mlb_draft_cache/2010.json
data/mlb_draft_cache/2011.json
data/mlb_draft_cache/2012.json
data/mlb_draft_cache/2013.json
data/mlb_draft_cache/2014.json
data/mlb_draft_cache/2015.json
data/mlb_draft_cache/2016.json
data/mlb_draft_cache/2017.json
data/mlb_draft_cache/2018.json
data/mlb_draft_cache/2019.json
data/mlb_draft_cache/2020.json
data/mlb_draft_cache/2021.json
data/mlb_draft_cache/2022.json
data/mlb_draft_cache/2023.json
data/mlb_draft_cache/2024.json
data/mlb_draft_cache/2025.json
data/mlb_draft_cache/all_drafts.json
data/mlb_team_names/drafted_by_teams.csv
ncaa_bbstats-1.1.0.dist-info/licenses/LICENSE
ncaa_bbstats-1.1.0.dist-info/METADATA
ncaa_bbstats-1.1.0.dist-info/WHEEL
ncaa_bbstats-1.1.0.dist-info/entry_points.txt
ncaa_bbstats-1.1.0.dist-info/top_level.txt
ncaa_bbstats-1.1.0.dist-info/RECORD
