Metadata-Version: 2.4
Name: ncaa_bbStats
Version: 1.1.0
Summary: A package to analyze college baseball stats by year and division
Author-email: Mateo Biggs <mateojohn2024@gmail.com>
License: MIT
Project-URL: GitHub, https://github.com/CodeMateo15/CollegeBaseballStatsPackage
Project-URL: Documentation, https://collegebaseballstatspackage.readthedocs.io/en/latest/index.html
Requires-Python: >=3.8
License-File: LICENSE
Requires-Dist: matplotlib
Requires-Dist: numpy
Requires-Dist: pandas>=1.3
Dynamic: license-file
